etherdata_sdk/__init__.py
etherdata_sdk/types.py
etherdata_sdk/account/__init__.py
etherdata_sdk/account/account.py
etherdata_sdk/account/api.py
etherdata_sdk/account/create.py
etherdata_sdk/account/save.py
etherdata_sdk/account/sign.py
etherdata_sdk/exception/__init__.py
etherdata_sdk/exception/rpc.py
etherdata_sdk/file/__init__.py
etherdata_sdk/file/api.py
etherdata_sdk/file/download.py
etherdata_sdk/file/file.py
etherdata_sdk/file/upload_create.py
etherdata_sdk/json_rpc/__init__.py
etherdata_sdk/json_rpc/admin.py
etherdata_sdk/json_rpc/clique.py
etherdata_sdk/json_rpc/debug.py
etherdata_sdk/json_rpc/etd.py
etherdata_sdk/json_rpc/json_rpc.py
etherdata_sdk/json_rpc/json_rpc_methods.py
etherdata_sdk/json_rpc/miner.py
etherdata_sdk/json_rpc/personal.py
etherdata_sdk/json_rpc/real_time.py
etherdata_sdk/json_rpc/txpool.py
etherdata_sdk/utils/__init__.py
etherdata_sdk/utils/to_dict.py
examples/__init__.py
examples/file_example.py
examples/json_rpc_example.py
tests/__init__.py
tests/test_account.py
tests/test_api.py
tests/test_file.py
tests/test_json_rpc.py
tests/test_utils.py
etherdata_sdk_python-5.1.3.dist-info/METADATA
etherdata_sdk_python-5.1.3.dist-info/WHEEL
etherdata_sdk_python-5.1.3.dist-info/top_level.txt
etherdata_sdk_python-5.1.3.dist-info/RECORD
