Metadata-Version: 2.1
Name: etherdata-sdk-python
Version: 5.1.3
Summary: SDK for etherdata-blockchain
Home-page: https://github.com/etherdata-blockchain/etherdata-sdk
Author: etherdata-blockchain
Author-email: etherdata-blockchain@etd.com
License: UNKNOWN
Project-URL: Bug Tracker, https://github.com/etherdata-blockchain/etherdata-sdk
Platform: UNKNOWN
Classifier: Programming Language :: Python :: 3
Classifier: License :: OSI Approved :: MIT License
Classifier: Operating System :: OS Independent
Requires-Python: >=3.6
Requires-Dist: requests (>=2.0.0)
Requires-Dist: dataclasses-json (>=0.5.6)
Requires-Dist: eth-account (==0.6.1)
